{
    "notification_groups":[
        {
            "key": "account",
            "name":"Account",
            "description": "Account related notifications",
            "display": true,
            "notifications": [
                {
                    "key": "invitation_sent",
                    "description":"Lorem ipsum dolor sit amet, consectetur adipiscing elit. Donec sollicitudin eu orci faucibus vulputate. In ut tincidunt mi, nec dignissim.",
                    "default": true,
                    "name": "Invitation Sent"
                },
                {
                    "key": "invitation_accepted",
                    "description":"Lorem ipsum dolor sit amet, consectetur adipiscing elit. Donec sollicitudin eu orci faucibus vulputate. In ut tincidunt mi, nec dignissim.",
                    "default": true,
                    "name": "Invitation Accepted"
                }
            ]
        },
        {
            "key": "crm",
            "name":"CRM",
            "description": "CRM related notifications",
            "display": true,
            "notifications":[
                {
                    "key":"lead",
                    "description":"Lorem ipsum dolor sit amet, consectetur adipiscing elit. Donec sollicitudin eu orci faucibus vulputate. In ut tincidunt mi, nec dignissim.",
                    "default": true,
                    "name": "Lead"
                },
                {
                    "key": "order",
                    "description":"Lorem ipsum dolor sit amet, consectetur adipiscing elit. Donec sollicitudin eu orci faucibus vulputate. In ut tincidunt mi, nec dignissim.",
                    "default": true,
                    "name": "Order"
                },
                {
                    "key":"upsell",
                    "description":"Lorem ipsum dolor sit amet, consectetur adipiscing elit. Donec sollicitudin eu orci faucibus vulputate. In ut tincidunt mi, nec dignissim.",
                    "default": true,
                    "name": "Upsell"
                },
                {
                    "key": "fail",
                    "description":"Lorem ipsum dolor sit amet, consectetur adipiscing elit. Donec sollicitudin eu orci faucibus vulputate. In ut tincidunt mi, nec dignissim.",
                    "default": true,
                    "name": "Fail"
                },
                {
                    "key": "cancellation",
                    "description":"Lorem ipsum dolor sit amet, consectetur adipiscing elit. Donec sollicitudin eu orci faucibus vulputate. In ut tincidunt mi, nec dignissim.",
                    "default": true,
                    "name": "Cancellation"
                },
                {
                    "key": "rebill",
                    "description":"Lorem ipsum dolor sit amet, consectetur adipiscing elit. Donec sollicitudin eu orci faucibus vulputate. In ut tincidunt mi, nec dignissim.",
                    "default": true,
                    "name": "Rebill"
                },
                {
                    "key": "mid",
                    "description":"Lorem ipsum dolor sit amet, consectetur adipiscing elit. Donec sollicitudin eu orci faucibus vulputate. In ut tincidunt mi, nec dignissim.",
                    "default": true,
                    "name": "Merchant Processor"
                }
            ]
        }
    ]
}
