{"transactions":[{"datetime":"2018-01-01T00:00:00.000Z","byprocessorresult":[{"processor_result":"error","count":"0","amount":"0"},{"processor_result":"fail","count":"0","amount":"0"},{"processor_result":"success","count":"0","amount":"0"}]},{"datetime":"2018-01-02T00:00:00.000Z","byprocessorresult":[{"processor_result":"error","count":"0","amount":"0"},{"processor_result":"fail","count":"0","amount":"0"},{"processor_result":"success","count":"0","amount":"0"}]},{"datetime":"2018-01-03T00:00:00.000Z","byprocessorresult":[{"processor_result":"error","count":"0","amount":"0"},{"processor_result":"fail","count":"0","amount":"0"},{"processor_result":"success","count":"0","amount":"0"}]},{"datetime":"2018-01-04T00:00:00.000Z","byprocessorresult":[{"processor_result":"error","count":"0","amount":"0"},{"processor_result":"fail","count":"0","amount":"0"},{"processor_result":"success","count":"0","amount":"0"}]},{"datetime":"2018-01-05T00:00:00.000Z","byprocessorresult":[{"processor_result":"error","count":"0","amount":"0"},{"processor_result":"fail","count":"0","amount":"0"},{"processor_result":"success","count":"0","amount":"0"}]},{"datetime":"2018-01-06T00:00:00.000Z","byprocessorresult":[{"processor_result":"error","count":"0","amount":"0"},{"processor_result":"fail","count":"0","amount":"0"},{"processor_result":"success","count":"0","amount":"0"}]},{"datetime":"2018-01-07T00:00:00.000Z","byprocessorresult":[{"processor_result":"error","count":"0","amount":"0"},{"processor_result":"fail","count":"0","amount":"0"},{"processor_result":"success","count":"0","amount":"0"}]},{"datetime":"2018-01-08T00:00:00.000Z","byprocessorresult":[{"processor_result":"error","count":"0","amount":"0"},{"processor_result":"fail","count":"0","amount":"0"},{"processor_result":"success","count":"0","amount":"0"}]},{"datetime":"2018-01-09T00:00:00.000Z","byprocessorresult":[{"processor_result":"error","count":"0","amount":"0"},{"processor_result":"fail","count":"0","amount":"0"},{"processor_result":"success","count":"0","amount":"0"}]},{"datetime":"2018-01-10T00:00:00.000Z","byprocessorresult":[{"processor_result":"error","count":"0","amount":"0"},{"processor_result":"fail","count":"0","amount":"0"},{"processor_result":"success","count":"0","amount":"0"}]},{"datetime":"2018-01-11T00:00:00.000Z","byprocessorresult":[{"processor_result":"error","count":"0","amount":"0"},{"processor_result":"fail","count":"0","amount":"0"},{"processor_result":"success","count":"0","amount":"0"}]},{"datetime":"2018-01-12T00:00:00.000Z","byprocessorresult":[{"processor_result":"error","count":"0","amount":"0"},{"processor_result":"fail","count":"0","amount":"0"},{"processor_result":"success","count":"0","amount":"0"}]},{"datetime":"2018-01-13T00:00:00.000Z","byprocessorresult":[{"processor_result":"error","count":"0","amount":"0"},{"processor_result":"fail","count":"0","amount":"0"},{"processor_result":"success","count":"0","amount":"0"}]},{"datetime":"2018-01-14T00:00:00.000Z","byprocessorresult":[{"processor_result":"error","count":"0","amount":"0"},{"processor_result":"fail","count":"0","amount":"0"},{"processor_result":"success","count":"0","amount":"0"}]},{"datetime":"2018-01-15T00:00:00.000Z","byprocessorresult":[{"processor_result":"error","count":"0","amount":"0"},{"processor_result":"fail","count":"0","amount":"0"},{"processor_result":"success","count":"0","amount":"0"}]},{"datetime":"2018-01-16T00:00:00.000Z","byprocessorresult":[{"processor_result":"error","count":"0","amount":"0"},{"processor_result":"fail","count":"0","amount":"0"},{"processor_result":"success","count":"0","amount":"0"}]},{"datetime":"2018-01-17T00:00:00.000Z","byprocessorresult":[{"processor_result":"error","count":"0","amount":"0"},{"processor_result":"fail","count":"0","amount":"0"},{"processor_result":"success","count":"0","amount":"0"}]},{"datetime":"2018-01-18T00:00:00.000Z","byprocessorresult":[{"processor_result":"error","count":"0","amount":"0"},{"processor_result":"fail","count":"0","amount":"0"},{"processor_result":"success","count":"0","amount":"0"}]},{"datetime":"2018-01-19T00:00:00.000Z","byprocessorresult":[{"processor_result":"error","count":"0","amount":"0"},{"processor_result":"fail","count":"0","amount":"0"},{"processor_result":"success","count":"0","amount":"0"}]},{"datetime":"2018-01-20T00:00:00.000Z","byprocessorresult":[{"processor_result":"error","count":"0","amount":"0"},{"processor_result":"fail","count":"0","amount":"0"},{"processor_result":"success","count":"0","amount":"0"}]},{"datetime":"2018-01-21T00:00:00.000Z","byprocessorresult":[{"processor_result":"error","count":"0","amount":"0"},{"processor_result":"fail","count":"0","amount":"0"},{"processor_result":"success","count":"0","amount":"0"}]},{"datetime":"2018-01-22T00:00:00.000Z","byprocessorresult":[{"processor_result":"error","count":"0","amount":"0"},{"processor_result":"fail","count":"0","amount":"0"},{"processor_result":"success","count":"30","amount":"1784.54"}]},{"datetime":"2018-01-23T00:00:00.000Z","byprocessorresult":[{"processor_result":"error","count":"0","amount":"0"},{"processor_result":"fail","count":"0","amount":"0"},{"processor_result":"success","count":"0","amount":"0"}]},{"datetime":"2018-01-24T00:00:00.000Z","byprocessorresult":[{"processor_result":"error","count":"0","amount":"0"},{"processor_result":"fail","count":"0","amount":"0"},{"processor_result":"success","count":"0","amount":"0"}]},{"datetime":"2018-01-25T00:00:00.000Z","byprocessorresult":[{"processor_result":"error","count":"0","amount":"0"},{"processor_result":"fail","count":"0","amount":"0"},{"processor_result":"success","count":"0","amount":"0"}]},{"datetime":"2018-01-26T00:00:00.000Z","byprocessorresult":[{"processor_result":"error","count":"0","amount":"0"},{"processor_result":"fail","count":"0","amount":"0"},{"processor_result":"success","count":"0","amount":"0"}]},{"datetime":"2018-01-27T00:00:00.000Z","byprocessorresult":[{"processor_result":"error","count":"0","amount":"0"},{"processor_result":"fail","count":"0","amount":"0"},{"processor_result":"success","count":"0","amount":"0"}]},{"datetime":"2018-01-28T00:00:00.000Z","byprocessorresult":[{"processor_result":"error","count":"0","amount":"0"},{"processor_result":"fail","count":"0","amount":"0"},{"processor_result":"success","count":"0","amount":"0"}]},{"datetime":"2018-01-29T00:00:00.000Z","byprocessorresult":[{"processor_result":"error","count":"0","amount":"0"},{"processor_result":"fail","count":"0","amount":"0"},{"processor_result":"success","count":"0","amount":"0"}]},{"datetime":"2018-01-30T00:00:00.000Z","byprocessorresult":[{"processor_result":"error","count":"0","amount":"0"},{"processor_result":"fail","count":"0","amount":"0"},{"processor_result":"success","count":"0","amount":"0"}]},{"datetime":"2018-01-31T00:00:00.000Z","byprocessorresult":[{"processor_result":"error","count":"0","amount":"0"},{"processor_result":"fail","count":"0","amount":"0"},{"processor_result":"success","count":"0","amount":"0"}]},{"datetime":"2018-02-01T00:00:00.000Z","byprocessorresult":[{"processor_result":"error","count":"0","amount":"0"},{"processor_result":"fail","count":"0","amount":"0"},{"processor_result":"success","count":"0","amount":"0"}]}]}