{
    "Table": {
        "TableName": "campaigns",
        "KeySchema": [{
            "AttributeName": "id",
            "KeyType": "HASH"
        }], 
        "AttributeDefinitions": [{
            "AttributeName": "id", 
            "AttributeType": "S"
        }],
        "ProvisionedThroughput": {
            "ReadCapacityUnits": 1, 
            "WriteCapacityUnits": 1
        }
    },
    "Seeds": [{
    	"id":"70a6689a-5814-438b-b9fd-dd484d0812f9",
    	"name": "Example Campaign",
    	"productschedules":["12529a17-ac32-4e46-b05b-83862843055d"],
    	"loadbalancer":"927b4f7c-b0e9-4ddb-a05c-ba81d2d663d3"
    }]
}
